ragui/__init__.py
ragui/_cli.py
ragui/_server.py
ragui/templates/websocket_test.html
ragui-0.1.0.dist-info/METADATA
ragui-0.1.0.dist-info/WHEEL
ragui-0.1.0.dist-info/entry_points.txt
ragui-0.1.0.dist-info/licenses/LICENSE
ragui-0.1.0.dist-info/RECORD
