Metadata-Version: 2.4
Name: ragui
Version: 0.1.0
Summary: Add your description here
Author-email: Spyros Avlonitis <spyrosavl@gmail.com>
License-File: LICENSE
Requires-Python: >=3.12
Requires-Dist: fastapi[standard]>=0.115.6
Requires-Dist: itsdangerous>=2.2.0
Requires-Dist: jinja2>=3.1.4
Requires-Dist: pydantic>=2.10.3
Requires-Dist: sqlmodel>=0.0.22
Requires-Dist: typer>=0.15.1
Requires-Dist: uvicorn>=0.34.0
